form_scrapper/__init__.py
form_scrapper/config.py
form_scrapper/form_scrapper.py
form_scrapper/question.py
form_scrapper/utils.py
form_scrapper-0.2.0.dist-info/LICENSE
form_scrapper-0.2.0.dist-info/METADATA
form_scrapper-0.2.0.dist-info/WHEEL
form_scrapper-0.2.0.dist-info/top_level.txt
form_scrapper-0.2.0.dist-info/RECORD
