Metadata-Version: 2.1
Name: form-scrapper
Version: 0.2.0
Summary: A package to scrape Google Forms and extract questions.
Home-page: UNKNOWN
Author: Yannick Rafael
License: UNKNOWN
Platform: UNKNOWN
License-File: LICENSE
Requires-Dist: requests
Requires-Dist: beautifulsoup4
Requires-Dist: regex
